opensbt/__init__.py
opensbt/config.py
opensbt/version.py
opensbt/algorithm/__init__.py
opensbt/algorithm/algorithm.py
opensbt/algorithm/nsga2_optimizer.py
opensbt/algorithm/nsga2dt_optimizer.py
opensbt/algorithm/optimizer.py
opensbt/algorithm/ps.py
opensbt/algorithm/ps_fps.py
opensbt/algorithm/ps_grid.py
opensbt/algorithm/ps_rand.py
opensbt/algorithm/pso_optimizer.py
opensbt/algorithm/classification/__init__.py
opensbt/algorithm/classification/classifier.py
opensbt/algorithm/classification/decision_tree/__init__.py
opensbt/algorithm/classification/decision_tree/decision_tree.py
opensbt/evaluation/__init__.py
opensbt/evaluation/critical.py
opensbt/evaluation/fitness.py
opensbt/exception/__init__.py
opensbt/exception/configuration.py
opensbt/experiment/__init__.py
opensbt/experiment/experiment.py
opensbt/experiment/experiment_store.py
opensbt/experiment/search_configuration.py
opensbt/model_ga/__init__.py
opensbt/model_ga/individual.py
opensbt/model_ga/population.py
opensbt/model_ga/problem.py
opensbt/model_ga/result.py
opensbt/problem/__init__.py
opensbt/problem/adas_problem.py
opensbt/problem/pymoo_test_problem.py
opensbt/quality_indicators/__init__.py
opensbt/quality_indicators/quality.py
opensbt/quality_indicators/metrics/__init__.py
opensbt/quality_indicators/metrics/spread.py
opensbt/simulation/__init__.py
opensbt/simulation/dummy_simulation.py
opensbt/simulation/simulator.py
opensbt/utils/__init__.py
opensbt/utils/duplicates.py
opensbt/utils/evaluation.py
opensbt/utils/fps.py
opensbt/utils/geometric.py
opensbt/utils/log_utils.py
opensbt/utils/path.py
opensbt/utils/sampling.py
opensbt/utils/sorting.py
opensbt/utils/time_utils.py
opensbt/visualization/__init__.py
opensbt/visualization/configuration.py
opensbt/visualization/scenario_plotter.py
opensbt/visualization/visualizer.py
opensbt-0.1.4.dist-info/LICENSE
opensbt-0.1.4.dist-info/METADATA
opensbt-0.1.4.dist-info/WHEEL
opensbt-0.1.4.dist-info/top_level.txt
opensbt-0.1.4.dist-info/RECORD
