Metadata-Version: 2.1
Name: opensbt
Version: 0.1.4
Summary: OpenSBT is a Modular Framework for Search-based Testing of Automated Driving Systems
Home-page: https://git.fortiss.org/opensbt/opensbt-core
Author: Lev Sorokin
Author-email: sorokin@fortiss.org
License: Apache
Classifier: Programming Language :: Python :: 3.8
Classifier: Programming Language :: Python :: 3.9
Classifier: License :: OSI Approved :: Apache Software License
Classifier: Operating System :: POSIX :: Linux
Classifier: Topic :: Software Development :: Testing
Classifier: Topic :: Software Development :: Testing :: Acceptance
Classifier: Topic :: Scientific/Engineering
Requires-Python: >=3.8
License-File: LICENSE
Requires-Dist: deap ==1.4.1
Requires-Dist: numpy ==1.24.4
Requires-Dist: scipy ==1.10.1
Requires-Dist: matplotlib ==3.7.4
Requires-Dist: pandas ==2.0.3
Requires-Dist: setuptools
Requires-Dist: scikit-learn ==1.3.2
Requires-Dist: pymoo ==0.6.0.1
